{
  "project_info": {
    "project_number": "1039312561244",
    "project_id": "instagram-a51fb",
    "storage_bucket": "instagram-a51fb.firebasestorage.app"
  },
  "client": [
    {
      "client_info": {
        "mobilesdk_app_id": "1:1039312561244:android:534a4524b4089efc083299",
        "android_client_info": {
          "package_name": "com.example.insta"
        }
      },
      "oauth_client": [],
      "api_key": [
        {
          "current_key": "AIzaSyBRnpx6QW4QBqTzJCxHCF5xrMOMJeysoPE"
        }
      ],
      "services": {
        "appinvite_service": {
          "other_platform_oauth_client": []
        }
      }
    }
  ],
  "configuration_version": "1"
}